Metadata-Version: 2.1
Name: gh-announce
Version: 0.0.3
Summary: Twitter bot that posts a tweet each time you make a release on github!
Home-page: https://github.com/prahladyeri/gh_announce
Author: Prahlad Yeri
Author-email: prahladyeri@yahoo.com
License: MIT
Keywords: github,twitter,internet
Platform: UNKNOWN
Classifier: Programming Language :: Python :: 3
Classifier: License :: OSI Approved :: MIT License
Classifier: Operating System :: OS Independent
